<?xml version="1.0" encoding="UTF-8"?>
<theme>
   <formatVersion>7</formatVersion>
   <view name="system,basic">
      <image name="background-art" extra="true">
         <path>./../../../../_inc/images/systems/default/default-centered-background.png</path>
         <path>./../../../../_inc/images/systems/centered/${system.theme}-art.png</path>
         <path ifSubset="alternative-background-images:on">./../../../../_inc/images/systems/centered/alt/${system.theme}-art.png</path>
         <path ifSubset="alternative-background-images:custom">~/roms/themes/art-book-next/custom/${system.theme}-art.png</path>
         <size>0 1</size>
      </image>
   </view>
   <view ifSubset="alternative-background-images:custom" name="system">
      <image name="custom-background-art-mask" extra="true">
         <path>./../../../../_inc/images/utility/centered-background-custom-mask.svg</path>
         <size>0 1</size>
         <origin>0 0.5</origin>
         <pos>0 0.5</pos>
      </image>
   </view>
   <view name="basic">
      <image name="background-art" extra="true">
         <path>./../../../../_inc/images/systems/default/default-fullscreen-background.jpg</path>
         <zIndex>0</zIndex>
         <color>ffffffcc</color>
      </image>
   </view>
</theme>